hunter_sdk/Hunter.py
hunter_sdk/HunterApi.py
hunter_sdk/__init__.py
hunter_sdk/Common/BaseObject.py
hunter_sdk/Common/HunterObject.py
hunter_sdk/Common/__init__.py
hunter_sdk-0.0.9.dist-info/LICENSE
hunter_sdk-0.0.9.dist-info/METADATA
hunter_sdk-0.0.9.dist-info/WHEEL
hunter_sdk-0.0.9.dist-info/top_level.txt
hunter_sdk-0.0.9.dist-info/zip-safe
hunter_sdk-0.0.9.dist-info/RECORD
