Metadata-Version: 2.1
Name: hunter-sdk
Version: 0.0.9
Summary: Hunter SDK
Home-page: https://github.com/SpenserCai/Hunter-SDK
Author: spensercai
Author-email: spensercai@gmail.com
License: MIT
Platform: UNKNOWN
License-File: LICENSE
